dolphins/__init__.py
dolphins/ml_models.py
dolphins/data/customers.csv
dolphins/data/student_performance.csv
dolphins-0.1.0.dist-info/METADATA
dolphins-0.1.0.dist-info/WHEEL
dolphins-0.1.0.dist-info/top_level.txt
dolphins-0.1.0.dist-info/RECORD
