Metadata-Version: 2.4
Name: dolphins
Version: 0.1.0
Summary: The thrill isn’t in winning—it’s in bending the system without leaving a mark.
Author: Δrj★n
Requires-Python: >=3.6
Dynamic: author
Dynamic: requires-python
Dynamic: summary
